vstt/__init__.py
vstt/__main__.py
vstt/common.py
vstt/display.py
vstt/display_widget.py
vstt/experiment.py
vstt/geom.py
vstt/gui.py
vstt/joystick_wrapper.py
vstt/meta.py
vstt/meta_widget.py
vstt/py.typed
vstt/results_widget.py
vstt/stats.py
vstt/task.py
vstt/trial.py
vstt/trials_widget.py
vstt/update.py
vstt/vis.py
vstt/vtypes.py
vstt-1.6.0.dist-info/licenses/LICENSE
vstt-1.6.0.dist-info/METADATA
vstt-1.6.0.dist-info/WHEEL
vstt-1.6.0.dist-info/entry_points.txt
vstt-1.6.0.dist-info/top_level.txt
vstt-1.6.0.dist-info/RECORD
