Metadata-Version: 2.4
Name: vstt
Version: 1.6.0
Summary: Visuomotor Serial Targeting Task (VSTT)
Author-email: Liam Keegan <ssc@iwr.uni-heidelberg.de>
License: MIT
Project-URL: Github, https://github.com/ssciwr/vstt
Project-URL: Issues, https://github.com/ssciwr/vstt/issues
Project-URL: Documentation, https://vstt.readthedocs.io/
Classifier: Topic :: Scientific/Engineering :: Bio-Informatics
Classifier: License :: OSI Approved :: MIT License
Classifier: Intended Audience :: Science/Research
Classifier: Intended Audience :: Education
Classifier: Natural Language :: English
Classifier: Operating System :: MacOS :: MacOS X
Classifier: Operating System :: Microsoft :: Windows
Classifier: Operating System :: POSIX :: Linux
Classifier: Programming Language :: Python :: 3 :: Only
Classifier: Programming Language :: Python :: 3.7
Classifier: Programming Language :: Python :: 3.8
Classifier: Programming Language :: Python :: 3.9
Classifier: Programming Language :: Python :: 3.10
Classifier: Programming Language :: Python :: 3.11
Requires-Python: >=3.7
License-File: LICENSE
Requires-Dist: click
Requires-Dist: numpy
Requires-Dist: packaging
Requires-Dist: pillow
Requires-Dist: psychopy
Requires-Dist: qtpy
Requires-Dist: requests
Requires-Dist: shapely
Provides-Extra: tests
Requires-Dist: ascii-magic; extra == "tests"
Requires-Dist: keyboard; extra == "tests"
Requires-Dist: pyautogui; extra == "tests"
Requires-Dist: pytest; extra == "tests"
Requires-Dist: pytest-cov; extra == "tests"
Requires-Dist: pytest-randomly; extra == "tests"
Requires-Dist: pytest-qt; extra == "tests"
Requires-Dist: pytest_mock; extra == "tests"
Provides-Extra: docs
Requires-Dist: ipykernel; extra == "docs"
Requires-Dist: matplotlib; extra == "docs"
Requires-Dist: myst_parser; extra == "docs"
Requires-Dist: nbsphinx; extra == "docs"
Requires-Dist: pandoc; extra == "docs"
Requires-Dist: sphinx>=4.5.0; extra == "docs"
Requires-Dist: sphinx_rtd_theme>=1.0.0; extra == "docs"
Requires-Dist: ipywidgets; extra == "docs"
Dynamic: license-file
